{
  "data": [
    {
      "id": "dde9",
      "firstname": "dxfcgvhbome",
      "password": "dfgvhbj"
    },
    {
      "id": "c76f",
      "firstname": "dhvani",
      "password": "cvbnm,"
    },
    {
      "id": "d373",
      "firstname": "dfghjk",
      "password": "dfghjbk"
    },
    {
      "id": "db29",
      "firstname": "dhvani chhajed",
      "password": "dhani@52534"
    },
    {
      "id": "435c",
      "firstname": "rfghsd",
      "password": "ggvf"
    },
    {
      "id": "6849",
      "firstname": "rfghsd",
      "password": "ggvf"
    },
    {
      "id": "4765",
      "firstname": "drfghj",
      "password": "dfcgvhbj"
    },
    {
      "id": "fb97",
      "firstname": "fdghjk",
      "password": "dfghjk"
    }
  ]
}